{
    "active_lock_reason": null,
    "assignee": null,
    "assignees": [],
    "author_association": "MEMBER",
    "body": "Otherwise we might look suspicious.\r\n\r\nAlso important if we want to redirect the update checker. If that is possible.",
    "closed_at": "2024-12-03T17:47:08Z",
    "closed_by": {
        "avatar_url": "https://avatars.githubusercontent.com/u/10647936?v=4",
        "events_url": "https://api.github.com/users/iphydf/events{/privacy}",
        "followers_url": "https://api.github.com/users/iphydf/followers",
        "following_url": "https://api.github.com/users/iphydf/following{/other_user}",
        "gists_url": "https://api.github.com/users/iphydf/gists{/gist_id}",
        "gravatar_id": "",
        "html_url": "https://github.com/iphydf",
        "id": 10647936,
        "login": "iphydf",
        "node_id": "MDQ6VXNlcjEwNjQ3OTM2",
        "organizations_url": "https://api.github.com/users/iphydf/orgs",
        "received_events_url": "https://api.github.com/users/iphydf/received_events",
        "repos_url": "https://api.github.com/users/iphydf/repos",
        "site_admin": false,
        "starred_url": "https://api.github.com/users/iphydf/starred{/owner}{/repo}",
        "subscriptions_url": "https://api.github.com/users/iphydf/subscriptions",
        "type": "User",
        "url": "https://api.github.com/users/iphydf",
        "user_view_type": "public"
    },
    "comment_data": [],
    "comments": 0,
    "comments_url": "https://api.github.com/repos/TokTok/qTox/issues/156/comments",
    "created_at": "2024-11-25T17:19:41Z",
    "event_data": [
        {
            "actor": {
                "avatar_url": "https://avatars.githubusercontent.com/u/2938071?v=4",
                "events_url": "https://api.github.com/users/Green-Sky/events{/privacy}",
                "followers_url": "https://api.github.com/users/Green-Sky/followers",
                "following_url": "https://api.github.com/users/Green-Sky/following{/other_user}",
                "gists_url": "https://api.github.com/users/Green-Sky/gists{/gist_id}",
                "gravatar_id": "",
                "html_url": "https://github.com/Green-Sky",
                "id": 2938071,
                "login": "Green-Sky",
                "node_id": "MDQ6VXNlcjI5MzgwNzE=",
                "organizations_url": "https://api.github.com/users/Green-Sky/orgs",
                "received_events_url": "https://api.github.com/users/Green-Sky/received_events",
                "repos_url": "https://api.github.com/users/Green-Sky/repos",
                "site_admin": false,
                "starred_url": "https://api.github.com/users/Green-Sky/starred{/owner}{/repo}",
                "subscriptions_url": "https://api.github.com/users/Green-Sky/subscriptions",
                "type": "User",
                "url": "https://api.github.com/users/Green-Sky",
                "user_view_type": "public"
            },
            "commit_id": null,
            "commit_url": null,
            "created_at": "2024-11-25T17:19:41Z",
            "event": "labeled",
            "id": 15424123004,
            "label": {
                "color": "d93f0b",
                "name": "security"
            },
            "node_id": "LE_lADOA9gydM6gbYhZzwAAAAOXWXB8",
            "performed_via_github_app": null,
            "url": "https://api.github.com/repos/TokTok/qTox/issues/events/15424123004"
        },
        {
            "actor": {
                "avatar_url": "https://avatars.githubusercontent.com/u/2938071?v=4",
                "events_url": "https://api.github.com/users/Green-Sky/events{/privacy}",
                "followers_url": "https://api.github.com/users/Green-Sky/followers",
                "following_url": "https://api.github.com/users/Green-Sky/following{/other_user}",
                "gists_url": "https://api.github.com/users/Green-Sky/gists{/gist_id}",
                "gravatar_id": "",
                "html_url": "https://github.com/Green-Sky",
                "id": 2938071,
                "login": "Green-Sky",
                "node_id": "MDQ6VXNlcjI5MzgwNzE=",
                "organizations_url": "https://api.github.com/users/Green-Sky/orgs",
                "received_events_url": "https://api.github.com/users/Green-Sky/received_events",
                "repos_url": "https://api.github.com/users/Green-Sky/repos",
                "site_admin": false,
                "starred_url": "https://api.github.com/users/Green-Sky/starred{/owner}{/repo}",
                "subscriptions_url": "https://api.github.com/users/Green-Sky/subscriptions",
                "type": "User",
                "url": "https://api.github.com/users/Green-Sky",
                "user_view_type": "public"
            },
            "commit_id": null,
            "commit_url": null,
            "created_at": "2024-11-25T17:19:41Z",
            "event": "labeled",
            "id": 15424123009,
            "label": {
                "color": "f9d0c4",
                "name": "chore"
            },
            "node_id": "LE_lADOA9gydM6gbYhZzwAAAAOXWXCB",
            "performed_via_github_app": null,
            "url": "https://api.github.com/repos/TokTok/qTox/issues/events/15424123009"
        },
        {
            "actor": {
                "avatar_url": "https://avatars.githubusercontent.com/u/2938071?v=4",
                "events_url": "https://api.github.com/users/Green-Sky/events{/privacy}",
                "followers_url": "https://api.github.com/users/Green-Sky/followers",
                "following_url": "https://api.github.com/users/Green-Sky/following{/other_user}",
                "gists_url": "https://api.github.com/users/Green-Sky/gists{/gist_id}",
                "gravatar_id": "",
                "html_url": "https://github.com/Green-Sky",
                "id": 2938071,
                "login": "Green-Sky",
                "node_id": "MDQ6VXNlcjI5MzgwNzE=",
                "organizations_url": "https://api.github.com/users/Green-Sky/orgs",
                "received_events_url": "https://api.github.com/users/Green-Sky/received_events",
                "repos_url": "https://api.github.com/users/Green-Sky/repos",
                "site_admin": false,
                "starred_url": "https://api.github.com/users/Green-Sky/starred{/owner}{/repo}",
                "subscriptions_url": "https://api.github.com/users/Green-Sky/subscriptions",
                "type": "User",
                "url": "https://api.github.com/users/Green-Sky",
                "user_view_type": "public"
            },
            "commit_id": null,
            "commit_url": null,
            "created_at": "2024-11-25T17:19:41Z",
            "event": "milestoned",
            "id": 15424123026,
            "milestone": {
                "title": "v1.18.0"
            },
            "node_id": "MIE_lADOA9gydM6gbYhZzwAAAAOXWXCS",
            "performed_via_github_app": null,
            "url": "https://api.github.com/repos/TokTok/qTox/issues/events/15424123026"
        },
        {
            "actor": {
                "avatar_url": "https://avatars.githubusercontent.com/u/10647936?v=4",
                "events_url": "https://api.github.com/users/iphydf/events{/privacy}",
                "followers_url": "https://api.github.com/users/iphydf/followers",
                "following_url": "https://api.github.com/users/iphydf/following{/other_user}",
                "gists_url": "https://api.github.com/users/iphydf/gists{/gist_id}",
                "gravatar_id": "",
                "html_url": "https://github.com/iphydf",
                "id": 10647936,
                "login": "iphydf",
                "node_id": "MDQ6VXNlcjEwNjQ3OTM2",
                "organizations_url": "https://api.github.com/users/iphydf/orgs",
                "received_events_url": "https://api.github.com/users/iphydf/received_events",
                "repos_url": "https://api.github.com/users/iphydf/repos",
                "site_admin": false,
                "starred_url": "https://api.github.com/users/iphydf/starred{/owner}{/repo}",
                "subscriptions_url": "https://api.github.com/users/iphydf/subscriptions",
                "type": "User",
                "url": "https://api.github.com/users/iphydf",
                "user_view_type": "public"
            },
            "commit_id": null,
            "commit_url": null,
            "created_at": "2024-12-03T17:47:08Z",
            "event": "closed",
            "id": 15513947756,
            "node_id": "CE_lADOA9gydM6gbYhZzwAAAAOctA5s",
            "performed_via_github_app": null,
            "state_reason": null,
            "url": "https://api.github.com/repos/TokTok/qTox/issues/events/15513947756"
        }
    ],
    "events_url": "https://api.github.com/repos/TokTok/qTox/issues/156/events",
    "html_url": "https://github.com/TokTok/qTox/issues/156",
    "id": 2691532889,
    "labels": [
        {
            "color": "d93f0b",
            "default": false,
            "description": "Security",
            "id": 2013011623,
            "name": "security",
            "node_id": "MDU6TGFiZWwyMDEzMDExNjIz",
            "url": "https://api.github.com/repos/TokTok/qTox/labels/security"
        },
        {
            "color": "f9d0c4",
            "default": false,
            "description": "Updating grunt tasks etc; no production code change",
            "id": 2045790076,
            "name": "chore",
            "node_id": "MDU6TGFiZWwyMDQ1NzkwMDc2",
            "url": "https://api.github.com/repos/TokTok/qTox/labels/chore"
        }
    ],
    "labels_url": "https://api.github.com/repos/TokTok/qTox/issues/156/labels{/name}",
    "locked": false,
    "milestone": {
        "closed_at": "2025-01-01T18:54:11Z",
        "closed_issues": 267,
        "created_at": "2020-05-04T00:19:45Z",
        "creator": {
            "avatar_url": "https://avatars.githubusercontent.com/u/10647936?v=4",
            "events_url": "https://api.github.com/users/iphydf/events{/privacy}",
            "followers_url": "https://api.github.com/users/iphydf/followers",
            "following_url": "https://api.github.com/users/iphydf/following{/other_user}",
            "gists_url": "https://api.github.com/users/iphydf/gists{/gist_id}",
            "gravatar_id": "",
            "html_url": "https://github.com/iphydf",
            "id": 10647936,
            "login": "iphydf",
            "node_id": "MDQ6VXNlcjEwNjQ3OTM2",
            "organizations_url": "https://api.github.com/users/iphydf/orgs",
            "received_events_url": "https://api.github.com/users/iphydf/received_events",
            "repos_url": "https://api.github.com/users/iphydf/repos",
            "site_admin": false,
            "starred_url": "https://api.github.com/users/iphydf/starred{/owner}{/repo}",
            "subscriptions_url": "https://api.github.com/users/iphydf/subscriptions",
            "type": "User",
            "url": "https://api.github.com/users/iphydf",
            "user_view_type": "public"
        },
        "description": "",
        "due_on": null,
        "html_url": "https://github.com/TokTok/qTox/milestone/1",
        "id": 5377672,
        "labels_url": "https://api.github.com/repos/TokTok/qTox/milestones/1/labels",
        "node_id": "MDk6TWlsZXN0b25lNTM3NzY3Mg==",
        "number": 1,
        "open_issues": 0,
        "state": "closed",
        "title": "v1.18.0",
        "updated_at": "2025-01-16T08:13:58Z",
        "url": "https://api.github.com/repos/TokTok/qTox/milestones/1"
    },
    "node_id": "I_kwDOA9gydM6gbYhZ",
    "number": 156,
    "performed_via_github_app": null,
    "reactions": {
        "+1": 1,
        "-1": 0,
        "confused": 0,
        "eyes": 0,
        "heart": 0,
        "hooray": 0,
        "laugh": 0,
        "rocket": 0,
        "total_count": 1,
        "url": "https://api.github.com/repos/TokTok/qTox/issues/156/reactions"
    },
    "repository_url": "https://api.github.com/repos/TokTok/qTox",
    "state": "closed",
    "state_reason": "completed",
    "sub_issues_summary": {
        "completed": 0,
        "percent_completed": 0,
        "total": 0
    },
    "timeline_url": "https://api.github.com/repos/TokTok/qTox/issues/156/timeline",
    "title": "chore: add repo change to qtox about section",
    "updated_at": "2024-12-03T17:47:08Z",
    "url": "https://api.github.com/repos/TokTok/qTox/issues/156",
    "user": {
        "avatar_url": "https://avatars.githubusercontent.com/u/2938071?v=4",
        "events_url": "https://api.github.com/users/Green-Sky/events{/privacy}",
        "followers_url": "https://api.github.com/users/Green-Sky/followers",
        "following_url": "https://api.github.com/users/Green-Sky/following{/other_user}",
        "gists_url": "https://api.github.com/users/Green-Sky/gists{/gist_id}",
        "gravatar_id": "",
        "html_url": "https://github.com/Green-Sky",
        "id": 2938071,
        "login": "Green-Sky",
        "node_id": "MDQ6VXNlcjI5MzgwNzE=",
        "organizations_url": "https://api.github.com/users/Green-Sky/orgs",
        "received_events_url": "https://api.github.com/users/Green-Sky/received_events",
        "repos_url": "https://api.github.com/users/Green-Sky/repos",
        "site_admin": false,
        "starred_url": "https://api.github.com/users/Green-Sky/starred{/owner}{/repo}",
        "subscriptions_url": "https://api.github.com/users/Green-Sky/subscriptions",
        "type": "User",
        "url": "https://api.github.com/users/Green-Sky",
        "user_view_type": "public"
    }
}