{
    "_links": {
        "comments": {
            "href": "https://api.github.com/repos/TokTok/c-toxcore/issues/607/comments"
        },
        "commits": {
            "href": "https://api.github.com/repos/TokTok/c-toxcore/pulls/607/commits"
        },
        "html": {
            "href": "https://github.com/TokTok/c-toxcore/pull/607"
        },
        "issue": {
            "href": "https://api.github.com/repos/TokTok/c-toxcore/issues/607"
        },
        "review_comment": {
            "href": "https://api.github.com/repos/TokTok/c-toxcore/pulls/comments{/number}"
        },
        "review_comments": {
            "href": "https://api.github.com/repos/TokTok/c-toxcore/pulls/607/comments"
        },
        "self": {
            "href": "https://api.github.com/repos/TokTok/c-toxcore/pulls/607"
        },
        "statuses": {
            "href": "https://api.github.com/repos/TokTok/c-toxcore/statuses/bb5f8a17103537caa09bcf14130debe3210fb61f"
        }
    },
    "active_lock_reason": null,
    "additions": 1,
    "assignee": null,
    "assignees": [],
    "author_association": "MEMBER",
    "auto_merge": null,
    "base": {
        "label": "TokTok:master",
        "ref": "master",
        "repo": {
            "allow_forking": true,
            "archive_url": "https://api.github.com/repos/TokTok/c-toxcore/{archive_format}{/ref}",
            "archived": false,
            "assignees_url": "https://api.github.com/repos/TokTok/c-toxcore/assignees{/user}",
            "blobs_url": "https://api.github.com/repos/TokTok/c-toxcore/git/blobs{/sha}",
            "branches_url": "https://api.github.com/repos/TokTok/c-toxcore/branches{/branch}",
            "clone_url": "https://github.com/TokTok/c-toxcore.git",
            "collaborators_url": "https://api.github.com/repos/TokTok/c-toxcore/collaborators{/collaborator}",
            "comments_url": "https://api.github.com/repos/TokTok/c-toxcore/comments{/number}",
            "commits_url": "https://api.github.com/repos/TokTok/c-toxcore/commits{/sha}",
            "compare_url": "https://api.github.com/repos/TokTok/c-toxcore/compare/{base}...{head}",
            "contents_url": "https://api.github.com/repos/TokTok/c-toxcore/contents/{+path}",
            "contributors_url": "https://api.github.com/repos/TokTok/c-toxcore/contributors",
            "created_at": "2016-07-06T08:15:22Z",
            "default_branch": "master",
            "deployments_url": "https://api.github.com/repos/TokTok/c-toxcore/deployments",
            "description": "The future of online communications.",
            "disabled": false,
            "downloads_url": "https://api.github.com/repos/TokTok/c-toxcore/downloads",
            "events_url": "https://api.github.com/repos/TokTok/c-toxcore/events",
            "fork": true,
            "forks": 292,
            "forks_count": 292,
            "forks_url": "https://api.github.com/repos/TokTok/c-toxcore/forks",
            "full_name": "TokTok/c-toxcore",
            "git_commits_url": "https://api.github.com/repos/TokTok/c-toxcore/git/commits{/sha}",
            "git_refs_url": "https://api.github.com/repos/TokTok/c-toxcore/git/refs{/sha}",
            "git_tags_url": "https://api.github.com/repos/TokTok/c-toxcore/git/tags{/sha}",
            "git_url": "git://github.com/TokTok/c-toxcore.git",
            "has_discussions": false,
            "has_downloads": false,
            "has_issues": true,
            "has_pages": false,
            "has_projects": false,
            "has_wiki": false,
            "homepage": "https://tox.chat",
            "hooks_url": "https://api.github.com/repos/TokTok/c-toxcore/hooks",
            "html_url": "https://github.com/TokTok/c-toxcore",
            "id": 62703642,
            "is_template": false,
            "issue_comment_url": "https://api.github.com/repos/TokTok/c-toxcore/issues/comments{/number}",
            "issue_events_url": "https://api.github.com/repos/TokTok/c-toxcore/issues/events{/number}",
            "issues_url": "https://api.github.com/repos/TokTok/c-toxcore/issues{/number}",
            "keys_url": "https://api.github.com/repos/TokTok/c-toxcore/keys{/key_id}",
            "labels_url": "https://api.github.com/repos/TokTok/c-toxcore/labels{/name}",
            "language": "C",
            "languages_url": "https://api.github.com/repos/TokTok/c-toxcore/languages",
            "license": {
                "key": "gpl-3.0",
                "name": "GNU General Public License v3.0",
                "node_id": "MDc6TGljZW5zZTk=",
                "spdx_id": "GPL-3.0",
                "url": "https://api.github.com/licenses/gpl-3.0"
            },
            "merges_url": "https://api.github.com/repos/TokTok/c-toxcore/merges",
            "milestones_url": "https://api.github.com/repos/TokTok/c-toxcore/milestones{/number}",
            "mirror_url": null,
            "name": "c-toxcore",
            "node_id": "MDEwOlJlcG9zaXRvcnk2MjcwMzY0Mg==",
            "notifications_url": "https://api.github.com/repos/TokTok/c-toxcore/notifications{?since,all,participating}",
            "open_issues": 210,
            "open_issues_count": 210,
            "owner": {
                "avatar_url": "https://avatars.githubusercontent.com/u/17427091?v=4",
                "events_url": "https://api.github.com/users/TokTok/events{/privacy}",
                "followers_url": "https://api.github.com/users/TokTok/followers",
                "following_url": "https://api.github.com/users/TokTok/following{/other_user}",
                "gists_url": "https://api.github.com/users/TokTok/gists{/gist_id}",
                "gravatar_id": "",
                "html_url": "https://github.com/TokTok",
                "id": 17427091,
                "login": "TokTok",
                "node_id": "MDEyOk9yZ2FuaXphdGlvbjE3NDI3MDkx",
                "organizations_url": "https://api.github.com/users/TokTok/orgs",
                "received_events_url": "https://api.github.com/users/TokTok/received_events",
                "repos_url": "https://api.github.com/users/TokTok/repos",
                "site_admin": false,
                "starred_url": "https://api.github.com/users/TokTok/starred{/owner}{/repo}",
                "subscriptions_url": "https://api.github.com/users/TokTok/subscriptions",
                "type": "Organization",
                "url": "https://api.github.com/users/TokTok",
                "user_view_type": "public"
            },
            "private": false,
            "pulls_url": "https://api.github.com/repos/TokTok/c-toxcore/pulls{/number}",
            "pushed_at": "2025-01-24T18:18:40Z",
            "releases_url": "https://api.github.com/repos/TokTok/c-toxcore/releases{/id}",
            "size": 25245,
            "ssh_url": "git@github.com:TokTok/c-toxcore.git",
            "stargazers_count": 2329,
            "stargazers_url": "https://api.github.com/repos/TokTok/c-toxcore/stargazers",
            "statuses_url": "https://api.github.com/repos/TokTok/c-toxcore/statuses/{sha}",
            "subscribers_url": "https://api.github.com/repos/TokTok/c-toxcore/subscribers",
            "subscription_url": "https://api.github.com/repos/TokTok/c-toxcore/subscription",
            "svn_url": "https://github.com/TokTok/c-toxcore",
            "tags_url": "https://api.github.com/repos/TokTok/c-toxcore/tags",
            "teams_url": "https://api.github.com/repos/TokTok/c-toxcore/teams",
            "topics": [
                "cryptography",
                "encryption",
                "network",
                "p2p",
                "security",
                "toxcore"
            ],
            "trees_url": "https://api.github.com/repos/TokTok/c-toxcore/git/trees{/sha}",
            "updated_at": "2025-01-24T22:05:30Z",
            "url": "https://api.github.com/repos/TokTok/c-toxcore",
            "visibility": "public",
            "watchers": 2329,
            "watchers_count": 2329,
            "web_commit_signoff_required": false
        },
        "sha": "0542ffa2db75fc6affd1b5c83bcb5af8e7d92c88",
        "user": {
            "avatar_url": "https://avatars.githubusercontent.com/u/17427091?v=4",
            "events_url": "https://api.github.com/users/TokTok/events{/privacy}",
            "followers_url": "https://api.github.com/users/TokTok/followers",
            "following_url": "https://api.github.com/users/TokTok/following{/other_user}",
            "gists_url": "https://api.github.com/users/TokTok/gists{/gist_id}",
            "gravatar_id": "",
            "html_url": "https://github.com/TokTok",
            "id": 17427091,
            "login": "TokTok",
            "node_id": "MDEyOk9yZ2FuaXphdGlvbjE3NDI3MDkx",
            "organizations_url": "https://api.github.com/users/TokTok/orgs",
            "received_events_url": "https://api.github.com/users/TokTok/received_events",
            "repos_url": "https://api.github.com/users/TokTok/repos",
            "site_admin": false,
            "starred_url": "https://api.github.com/users/TokTok/starred{/owner}{/repo}",
            "subscriptions_url": "https://api.github.com/users/TokTok/subscriptions",
            "type": "Organization",
            "url": "https://api.github.com/users/TokTok",
            "user_view_type": "public"
        }
    },
    "body": "This complements #542 (and ought really to have been part of it). Currently, an\nannounce node will only accept an announce request if it has a current pingid,\nmeaning it must arrive within 20-40s of the last announce response sent by that\nnode. #542 increased the interval between announces in certain circumstances to\n120s. A pingid sent after such an interval will not be current. This means the\nannounce request fails, and so is followed (~3s later) by a second request with\na current pingid. This creates unnecessary extra traffic, and has the ugly\nconsequence that we appear to be unannounced for a few seconds (if we check\nthis, as the code currently does, by consulting the value of\nlist_nodes[i].is_stored).\n\nThis PR solves this problem by increasing the pingid timeout from 20s to 300s\n(which is the maximum time between announces required to keep the announce\nalive). This leaves room for increasing the 120s interval even further in the\nfuture.\n\nI can see no negative consequence of this change, but of course it's possible\nI'm missing something.\n\n<!-- Reviewable:start -->\n---\nThis change is [<img src=\"https://reviewable.io/review_button.svg\" height=\"34\" align=\"absmiddle\" alt=\"Reviewable\"/>](https://reviewable.io/reviews/toktok/c-toxcore/607)\n<!-- Reviewable:end -->\n",
    "changed_files": 1,
    "closed_at": "2017-11-04T15:03:48Z",
    "comment_data": [],
    "comment_regular_data": [
        {
            "author_association": "NONE",
            "body": "[![CLA assistant check](https://cla-assistant.io/pull/badge/signed)](https://cla-assistant.io/TokTok/c-toxcore?pullRequest=607) <br/>All committers have signed the CLA.",
            "created_at": "2017-10-28T12:40:55Z",
            "html_url": "https://github.com/TokTok/c-toxcore/pull/607#issuecomment-340188120",
            "id": 340188120,
            "issue_url": "https://api.github.com/repos/TokTok/c-toxcore/issues/607",
            "node_id": "MDEyOklzc3VlQ29tbWVudDM0MDE4ODEyMA==",
            "performed_via_github_app": null,
            "reactions": {
                "+1": 0,
                "-1": 0,
                "confused": 0,
                "eyes": 0,
                "heart": 0,
                "hooray": 0,
                "laugh": 0,
                "rocket": 0,
                "total_count": 0,
                "url": "https://api.github.com/repos/TokTok/c-toxcore/issues/comments/340188120/reactions"
            },
            "updated_at": "2018-12-30T19:29:27Z",
            "url": "https://api.github.com/repos/TokTok/c-toxcore/issues/comments/340188120",
            "user": {
                "avatar_url": "https://avatars.githubusercontent.com/u/11571300?v=4",
                "events_url": "https://api.github.com/users/CLAassistant/events{/privacy}",
                "followers_url": "https://api.github.com/users/CLAassistant/followers",
                "following_url": "https://api.github.com/users/CLAassistant/following{/other_user}",
                "gists_url": "https://api.github.com/users/CLAassistant/gists{/gist_id}",
                "gravatar_id": "",
                "html_url": "https://github.com/CLAassistant",
                "id": 11571300,
                "login": "CLAassistant",
                "node_id": "MDQ6VXNlcjExNTcxMzAw",
                "organizations_url": "https://api.github.com/users/CLAassistant/orgs",
                "received_events_url": "https://api.github.com/users/CLAassistant/received_events",
                "repos_url": "https://api.github.com/users/CLAassistant/repos",
                "site_admin": false,
                "starred_url": "https://api.github.com/users/CLAassistant/starred{/owner}{/repo}",
                "subscriptions_url": "https://api.github.com/users/CLAassistant/subscriptions",
                "type": "User",
                "url": "https://api.github.com/users/CLAassistant",
                "user_view_type": "public"
            }
        },
        {
            "author_association": "MEMBER",
            "body": "<img class=\"emoji\" title=\":lgtm_strong:\" alt=\":lgtm_strong:\" align=\"absmiddle\" src=\"https://reviewable.io/lgtm_strong.png\" height=\"20\" width=\"61\"/>\n\n---\n\nReviewed 1 of 1 files at r1.\nReview status: all files reviewed at latest revision, all discussions resolved, some commit checks broke.\n\n---\n\n\n\n*Comments from [Reviewable](https://reviewable.io:443/reviews/toktok/c-toxcore/607#-:-KxboShnoCOqBcIHw3Nc:b-jbsf8z)*\n<!-- Sent from Reviewable.io -->\n",
            "created_at": "2017-10-29T11:08:51Z",
            "html_url": "https://github.com/TokTok/c-toxcore/pull/607#issuecomment-340254055",
            "id": 340254055,
            "issue_url": "https://api.github.com/repos/TokTok/c-toxcore/issues/607",
            "node_id": "MDEyOklzc3VlQ29tbWVudDM0MDI1NDA1NQ==",
            "performed_via_github_app": null,
            "reactions": {
                "+1": 0,
                "-1": 0,
                "confused": 0,
                "eyes": 0,
                "heart": 0,
                "hooray": 0,
                "laugh": 0,
                "rocket": 0,
                "total_count": 0,
                "url": "https://api.github.com/repos/TokTok/c-toxcore/issues/comments/340254055/reactions"
            },
            "updated_at": "2017-10-29T11:08:51Z",
            "url": "https://api.github.com/repos/TokTok/c-toxcore/issues/comments/340254055",
            "user": {
                "avatar_url": "https://avatars.githubusercontent.com/u/8304462?v=4",
                "events_url": "https://api.github.com/users/robinlinden/events{/privacy}",
                "followers_url": "https://api.github.com/users/robinlinden/followers",
                "following_url": "https://api.github.com/users/robinlinden/following{/other_user}",
                "gists_url": "https://api.github.com/users/robinlinden/gists{/gist_id}",
                "gravatar_id": "",
                "html_url": "https://github.com/robinlinden",
                "id": 8304462,
                "login": "robinlinden",
                "node_id": "MDQ6VXNlcjgzMDQ0NjI=",
                "organizations_url": "https://api.github.com/users/robinlinden/orgs",
                "received_events_url": "https://api.github.com/users/robinlinden/received_events",
                "repos_url": "https://api.github.com/users/robinlinden/repos",
                "site_admin": false,
                "starred_url": "https://api.github.com/users/robinlinden/starred{/owner}{/repo}",
                "subscriptions_url": "https://api.github.com/users/robinlinden/subscriptions",
                "type": "User",
                "url": "https://api.github.com/users/robinlinden",
                "user_view_type": "public"
            }
        }
    ],
    "comments": 2,
    "comments_url": "https://api.github.com/repos/TokTok/c-toxcore/issues/607/comments",
    "commit_data": [
        {
            "author": {
                "avatar_url": "https://avatars.githubusercontent.com/u/590069?v=4",
                "events_url": "https://api.github.com/users/zugz/events{/privacy}",
                "followers_url": "https://api.github.com/users/zugz/followers",
                "following_url": "https://api.github.com/users/zugz/following{/other_user}",
                "gists_url": "https://api.github.com/users/zugz/gists{/gist_id}",
                "gravatar_id": "",
                "html_url": "https://github.com/zugz",
                "id": 590069,
                "login": "zugz",
                "node_id": "MDQ6VXNlcjU5MDA2OQ==",
                "organizations_url": "https://api.github.com/users/zugz/orgs",
                "received_events_url": "https://api.github.com/users/zugz/received_events",
                "repos_url": "https://api.github.com/users/zugz/repos",
                "site_admin": false,
                "starred_url": "https://api.github.com/users/zugz/starred{/owner}{/repo}",
                "subscriptions_url": "https://api.github.com/users/zugz/subscriptions",
                "type": "User",
                "url": "https://api.github.com/users/zugz",
                "user_view_type": "public"
            },
            "comments_url": "https://api.github.com/repos/TokTok/c-toxcore/commits/bb5f8a17103537caa09bcf14130debe3210fb61f/comments",
            "commit": {
                "author": {
                    "date": "2017-10-28T12:26:18Z",
                    "email": "mbays+tox@sdf.org",
                    "name": "zugz"
                },
                "comment_count": 0,
                "committer": {
                    "date": "2017-10-28T12:26:23Z",
                    "email": "mbays+tox@sdf.org",
                    "name": "zugz"
                },
                "message": "set onion pingid timeout to announce timeout (300s)",
                "tree": {
                    "sha": "f59f6b1efb3354eeab12a2ded3e67a90c716fd9a",
                    "url": "https://api.github.com/repos/TokTok/c-toxcore/git/trees/f59f6b1efb3354eeab12a2ded3e67a90c716fd9a"
                },
                "url": "https://api.github.com/repos/TokTok/c-toxcore/git/commits/bb5f8a17103537caa09bcf14130debe3210fb61f",
                "verification": {
                    "payload": null,
                    "reason": "unsigned",
                    "signature": null,
                    "verified": false,
                    "verified_at": null
                }
            },
            "committer": {
                "avatar_url": "https://avatars.githubusercontent.com/u/590069?v=4",
                "events_url": "https://api.github.com/users/zugz/events{/privacy}",
                "followers_url": "https://api.github.com/users/zugz/followers",
                "following_url": "https://api.github.com/users/zugz/following{/other_user}",
                "gists_url": "https://api.github.com/users/zugz/gists{/gist_id}",
                "gravatar_id": "",
                "html_url": "https://github.com/zugz",
                "id": 590069,
                "login": "zugz",
                "node_id": "MDQ6VXNlcjU5MDA2OQ==",
                "organizations_url": "https://api.github.com/users/zugz/orgs",
                "received_events_url": "https://api.github.com/users/zugz/received_events",
                "repos_url": "https://api.github.com/users/zugz/repos",
                "site_admin": false,
                "starred_url": "https://api.github.com/users/zugz/starred{/owner}{/repo}",
                "subscriptions_url": "https://api.github.com/users/zugz/subscriptions",
                "type": "User",
                "url": "https://api.github.com/users/zugz",
                "user_view_type": "public"
            },
            "html_url": "https://github.com/TokTok/c-toxcore/commit/bb5f8a17103537caa09bcf14130debe3210fb61f",
            "node_id": "MDY6Q29tbWl0Nzg5NTcyODg6YmI1ZjhhMTcxMDM1MzdjYWEwOWJjZjE0MTMwZGViZTMyMTBmYjYxZg==",
            "parents": [
                {
                    "html_url": "https://github.com/TokTok/c-toxcore/commit/0542ffa2db75fc6affd1b5c83bcb5af8e7d92c88",
                    "sha": "0542ffa2db75fc6affd1b5c83bcb5af8e7d92c88",
                    "url": "https://api.github.com/repos/TokTok/c-toxcore/commits/0542ffa2db75fc6affd1b5c83bcb5af8e7d92c88"
                }
            ],
            "sha": "bb5f8a17103537caa09bcf14130debe3210fb61f",
            "url": "https://api.github.com/repos/TokTok/c-toxcore/commits/bb5f8a17103537caa09bcf14130debe3210fb61f"
        }
    ],
    "commits": 1,
    "commits_url": "https://api.github.com/repos/TokTok/c-toxcore/pulls/607/commits",
    "created_at": "2017-10-28T12:40:49Z",
    "deletions": 1,
    "diff_url": "https://github.com/TokTok/c-toxcore/pull/607.diff",
    "draft": false,
    "head": {
        "label": "zugz:extendPingidTimeout",
        "ref": "extendPingidTimeout",
        "repo": {
            "allow_forking": true,
            "archive_url": "https://api.github.com/repos/zugz/c-toxcore/{archive_format}{/ref}",
            "archived": false,
            "assignees_url": "https://api.github.com/repos/zugz/c-toxcore/assignees{/user}",
            "blobs_url": "https://api.github.com/repos/zugz/c-toxcore/git/blobs{/sha}",
            "branches_url": "https://api.github.com/repos/zugz/c-toxcore/branches{/branch}",
            "clone_url": "https://github.com/zugz/c-toxcore.git",
            "collaborators_url": "https://api.github.com/repos/zugz/c-toxcore/collaborators{/collaborator}",
            "comments_url": "https://api.github.com/repos/zugz/c-toxcore/comments{/number}",
            "commits_url": "https://api.github.com/repos/zugz/c-toxcore/commits{/sha}",
            "compare_url": "https://api.github.com/repos/zugz/c-toxcore/compare/{base}...{head}",
            "contents_url": "https://api.github.com/repos/zugz/c-toxcore/contents/{+path}",
            "contributors_url": "https://api.github.com/repos/zugz/c-toxcore/contributors",
            "created_at": "2017-01-14T18:08:35Z",
            "default_branch": "master",
            "deployments_url": "https://api.github.com/repos/zugz/c-toxcore/deployments",
            "description": "The future of online communications.",
            "disabled": false,
            "downloads_url": "https://api.github.com/repos/zugz/c-toxcore/downloads",
            "events_url": "https://api.github.com/repos/zugz/c-toxcore/events",
            "fork": true,
            "forks": 0,
            "forks_count": 0,
            "forks_url": "https://api.github.com/repos/zugz/c-toxcore/forks",
            "full_name": "zugz/c-toxcore",
            "git_commits_url": "https://api.github.com/repos/zugz/c-toxcore/git/commits{/sha}",
            "git_refs_url": "https://api.github.com/repos/zugz/c-toxcore/git/refs{/sha}",
            "git_tags_url": "https://api.github.com/repos/zugz/c-toxcore/git/tags{/sha}",
            "git_url": "git://github.com/zugz/c-toxcore.git",
            "has_discussions": false,
            "has_downloads": true,
            "has_issues": false,
            "has_pages": false,
            "has_projects": true,
            "has_wiki": false,
            "homepage": "https://tox.chat/",
            "hooks_url": "https://api.github.com/repos/zugz/c-toxcore/hooks",
            "html_url": "https://github.com/zugz/c-toxcore",
            "id": 78957288,
            "is_template": false,
            "issue_comment_url": "https://api.github.com/repos/zugz/c-toxcore/issues/comments{/number}",
            "issue_events_url": "https://api.github.com/repos/zugz/c-toxcore/issues/events{/number}",
            "issues_url": "https://api.github.com/repos/zugz/c-toxcore/issues{/number}",
            "keys_url": "https://api.github.com/repos/zugz/c-toxcore/keys{/key_id}",
            "labels_url": "https://api.github.com/repos/zugz/c-toxcore/labels{/name}",
            "language": "C",
            "languages_url": "https://api.github.com/repos/zugz/c-toxcore/languages",
            "license": {
                "key": "gpl-3.0",
                "name": "GNU General Public License v3.0",
                "node_id": "MDc6TGljZW5zZTk=",
                "spdx_id": "GPL-3.0",
                "url": "https://api.github.com/licenses/gpl-3.0"
            },
            "merges_url": "https://api.github.com/repos/zugz/c-toxcore/merges",
            "milestones_url": "https://api.github.com/repos/zugz/c-toxcore/milestones{/number}",
            "mirror_url": null,
            "name": "c-toxcore",
            "node_id": "MDEwOlJlcG9zaXRvcnk3ODk1NzI4OA==",
            "notifications_url": "https://api.github.com/repos/zugz/c-toxcore/notifications{?since,all,participating}",
            "open_issues": 0,
            "open_issues_count": 0,
            "owner": {
                "avatar_url": "https://avatars.githubusercontent.com/u/590069?v=4",
                "events_url": "https://api.github.com/users/zugz/events{/privacy}",
                "followers_url": "https://api.github.com/users/zugz/followers",
                "following_url": "https://api.github.com/users/zugz/following{/other_user}",
                "gists_url": "https://api.github.com/users/zugz/gists{/gist_id}",
                "gravatar_id": "",
                "html_url": "https://github.com/zugz",
                "id": 590069,
                "login": "zugz",
                "node_id": "MDQ6VXNlcjU5MDA2OQ==",
                "organizations_url": "https://api.github.com/users/zugz/orgs",
                "received_events_url": "https://api.github.com/users/zugz/received_events",
                "repos_url": "https://api.github.com/users/zugz/repos",
                "site_admin": false,
                "starred_url": "https://api.github.com/users/zugz/starred{/owner}{/repo}",
                "subscriptions_url": "https://api.github.com/users/zugz/subscriptions",
                "type": "User",
                "url": "https://api.github.com/users/zugz",
                "user_view_type": "public"
            },
            "private": false,
            "pulls_url": "https://api.github.com/repos/zugz/c-toxcore/pulls{/number}",
            "pushed_at": "2022-07-10T15:28:21Z",
            "releases_url": "https://api.github.com/repos/zugz/c-toxcore/releases{/id}",
            "size": 16881,
            "ssh_url": "git@github.com:zugz/c-toxcore.git",
            "stargazers_count": 1,
            "stargazers_url": "https://api.github.com/repos/zugz/c-toxcore/stargazers",
            "statuses_url": "https://api.github.com/repos/zugz/c-toxcore/statuses/{sha}",
            "subscribers_url": "https://api.github.com/repos/zugz/c-toxcore/subscribers",
            "subscription_url": "https://api.github.com/repos/zugz/c-toxcore/subscription",
            "svn_url": "https://github.com/zugz/c-toxcore",
            "tags_url": "https://api.github.com/repos/zugz/c-toxcore/tags",
            "teams_url": "https://api.github.com/repos/zugz/c-toxcore/teams",
            "topics": [],
            "trees_url": "https://api.github.com/repos/zugz/c-toxcore/git/trees{/sha}",
            "updated_at": "2020-04-26T16:00:08Z",
            "url": "https://api.github.com/repos/zugz/c-toxcore",
            "visibility": "public",
            "watchers": 1,
            "watchers_count": 1,
            "web_commit_signoff_required": false
        },
        "sha": "bb5f8a17103537caa09bcf14130debe3210fb61f",
        "user": {
            "avatar_url": "https://avatars.githubusercontent.com/u/590069?v=4",
            "events_url": "https://api.github.com/users/zugz/events{/privacy}",
            "followers_url": "https://api.github.com/users/zugz/followers",
            "following_url": "https://api.github.com/users/zugz/following{/other_user}",
            "gists_url": "https://api.github.com/users/zugz/gists{/gist_id}",
            "gravatar_id": "",
            "html_url": "https://github.com/zugz",
            "id": 590069,
            "login": "zugz",
            "node_id": "MDQ6VXNlcjU5MDA2OQ==",
            "organizations_url": "https://api.github.com/users/zugz/orgs",
            "received_events_url": "https://api.github.com/users/zugz/received_events",
            "repos_url": "https://api.github.com/users/zugz/repos",
            "site_admin": false,
            "starred_url": "https://api.github.com/users/zugz/starred{/owner}{/repo}",
            "subscriptions_url": "https://api.github.com/users/zugz/subscriptions",
            "type": "User",
            "url": "https://api.github.com/users/zugz",
            "user_view_type": "public"
        }
    },
    "html_url": "https://github.com/TokTok/c-toxcore/pull/607",
    "id": 149333889,
    "issue_url": "https://api.github.com/repos/TokTok/c-toxcore/issues/607",
    "labels": [
        {
            "color": "84b6eb",
            "default": true,
            "description": "New feature for the user, not a new feature for build script",
            "id": 403702218,
            "name": "enhancement",
            "node_id": "MDU6TGFiZWw0MDM3MDIyMTg=",
            "url": "https://api.github.com/repos/TokTok/c-toxcore/labels/enhancement"
        },
        {
            "color": "eb6420",
            "default": false,
            "description": "High priority",
            "id": 406490359,
            "name": "P1",
            "node_id": "MDU6TGFiZWw0MDY0OTAzNTk=",
            "url": "https://api.github.com/repos/TokTok/c-toxcore/labels/P1"
        },
        {
            "color": "d4c5f9",
            "default": false,
            "description": "Network",
            "id": 438496130,
            "name": "network",
            "node_id": "MDU6TGFiZWw0Mzg0OTYxMzA=",
            "url": "https://api.github.com/repos/TokTok/c-toxcore/labels/network"
        }
    ],
    "locked": false,
    "maintainer_can_modify": false,
    "merge_commit_sha": "bb5f8a17103537caa09bcf14130debe3210fb61f",
    "mergeable": null,
    "mergeable_state": "unknown",
    "merged": true,
    "merged_at": "2017-11-04T15:03:48Z",
    "merged_by": {
        "avatar_url": "https://avatars.githubusercontent.com/u/8304462?v=4",
        "events_url": "https://api.github.com/users/robinlinden/events{/privacy}",
        "followers_url": "https://api.github.com/users/robinlinden/followers",
        "following_url": "https://api.github.com/users/robinlinden/following{/other_user}",
        "gists_url": "https://api.github.com/users/robinlinden/gists{/gist_id}",
        "gravatar_id": "",
        "html_url": "https://github.com/robinlinden",
        "id": 8304462,
        "login": "robinlinden",
        "node_id": "MDQ6VXNlcjgzMDQ0NjI=",
        "organizations_url": "https://api.github.com/users/robinlinden/orgs",
        "received_events_url": "https://api.github.com/users/robinlinden/received_events",
        "repos_url": "https://api.github.com/users/robinlinden/repos",
        "site_admin": false,
        "starred_url": "https://api.github.com/users/robinlinden/starred{/owner}{/repo}",
        "subscriptions_url": "https://api.github.com/users/robinlinden/subscriptions",
        "type": "User",
        "url": "https://api.github.com/users/robinlinden",
        "user_view_type": "public"
    },
    "milestone": {
        "closed_at": "2018-06-25T16:51:19Z",
        "closed_issues": 28,
        "created_at": "2017-08-05T17:45:52Z",
        "creator": {
            "avatar_url": "https://avatars.githubusercontent.com/u/8304462?v=4",
            "events_url": "https://api.github.com/users/robinlinden/events{/privacy}",
            "followers_url": "https://api.github.com/users/robinlinden/followers",
            "following_url": "https://api.github.com/users/robinlinden/following{/other_user}",
            "gists_url": "https://api.github.com/users/robinlinden/gists{/gist_id}",
            "gravatar_id": "",
            "html_url": "https://github.com/robinlinden",
            "id": 8304462,
            "login": "robinlinden",
            "node_id": "MDQ6VXNlcjgzMDQ0NjI=",
            "organizations_url": "https://api.github.com/users/robinlinden/orgs",
            "received_events_url": "https://api.github.com/users/robinlinden/received_events",
            "repos_url": "https://api.github.com/users/robinlinden/repos",
            "site_admin": false,
            "starred_url": "https://api.github.com/users/robinlinden/starred{/owner}{/repo}",
            "subscriptions_url": "https://api.github.com/users/robinlinden/subscriptions",
            "type": "User",
            "url": "https://api.github.com/users/robinlinden",
            "user_view_type": "public"
        },
        "description": "",
        "due_on": "2017-08-24T07:00:00Z",
        "html_url": "https://github.com/TokTok/c-toxcore/milestone/26",
        "id": 2682929,
        "labels_url": "https://api.github.com/repos/TokTok/c-toxcore/milestones/26/labels",
        "node_id": "MDk6TWlsZXN0b25lMjY4MjkyOQ==",
        "number": 26,
        "open_issues": 0,
        "state": "closed",
        "title": "v0.1.11",
        "updated_at": "2022-02-04T10:19:22Z",
        "url": "https://api.github.com/repos/TokTok/c-toxcore/milestones/26"
    },
    "node_id": "MDExOlB1bGxSZXF1ZXN0MTQ5MzMzODg5",
    "number": 607,
    "patch_url": "https://github.com/TokTok/c-toxcore/pull/607.patch",
    "rebaseable": null,
    "requested_reviewers": [],
    "requested_teams": [],
    "review_comment_url": "https://api.github.com/repos/TokTok/c-toxcore/pulls/comments{/number}",
    "review_comments": 0,
    "review_comments_url": "https://api.github.com/repos/TokTok/c-toxcore/pulls/607/comments",
    "state": "closed",
    "statuses_url": "https://api.github.com/repos/TokTok/c-toxcore/statuses/bb5f8a17103537caa09bcf14130debe3210fb61f",
    "title": "set onion pingid timeout to announce timeout (300s)",
    "updated_at": "2018-12-30T19:29:27Z",
    "url": "https://api.github.com/repos/TokTok/c-toxcore/pulls/607",
    "user": {
        "avatar_url": "https://avatars.githubusercontent.com/u/590069?v=4",
        "events_url": "https://api.github.com/users/zugz/events{/privacy}",
        "followers_url": "https://api.github.com/users/zugz/followers",
        "following_url": "https://api.github.com/users/zugz/following{/other_user}",
        "gists_url": "https://api.github.com/users/zugz/gists{/gist_id}",
        "gravatar_id": "",
        "html_url": "https://github.com/zugz",
        "id": 590069,
        "login": "zugz",
        "node_id": "MDQ6VXNlcjU5MDA2OQ==",
        "organizations_url": "https://api.github.com/users/zugz/orgs",
        "received_events_url": "https://api.github.com/users/zugz/received_events",
        "repos_url": "https://api.github.com/users/zugz/repos",
        "site_admin": false,
        "starred_url": "https://api.github.com/users/zugz/starred{/owner}{/repo}",
        "subscriptions_url": "https://api.github.com/users/zugz/subscriptions",
        "type": "User",
        "url": "https://api.github.com/users/zugz",
        "user_view_type": "public"
    }
}